README.rst
setup.py
pylatexparse/__init__.py
pylatexparse.egg-info/PKG-INFO
pylatexparse.egg-info/SOURCES.txt
pylatexparse.egg-info/dependency_links.txt
pylatexparse.egg-info/top_level.txt